artifact_experiment/__init__.py
artifact_experiment/_base/__init__.py
artifact_experiment/_base/components/__init__.py
artifact_experiment/_base/components/callbacks/__init__.py
artifact_experiment/_base/components/callbacks/artifact.py
artifact_experiment/_base/components/callbacks/base.py
artifact_experiment/_base/components/callbacks/cache.py
artifact_experiment/_base/components/callbacks/export.py
artifact_experiment/_base/components/callbacks/metadata.py
artifact_experiment/_base/components/callbacks/tracking.py
artifact_experiment/_base/components/factories/__init__.py
artifact_experiment/_base/components/factories/artifact.py
artifact_experiment/_base/components/handler_suites/__init__.py
artifact_experiment/_base/components/handler_suites/artifact.py
artifact_experiment/_base/components/handler_suites/base.py
artifact_experiment/_base/components/handler_suites/tracking.py
artifact_experiment/_base/components/handlers/__init__.py
artifact_experiment/_base/components/handlers/artifact.py
artifact_experiment/_base/components/handlers/base.py
artifact_experiment/_base/components/handlers/cache.py
artifact_experiment/_base/components/handlers/tracking.py
artifact_experiment/_base/components/plans/__init__.py
artifact_experiment/_base/components/plans/artifact.py
artifact_experiment/_base/components/plans/base.py
artifact_experiment/_base/components/plans/build_context.py
artifact_experiment/_base/components/resources/__init__.py
artifact_experiment/_base/components/resources/artifact.py
artifact_experiment/_base/components/resources/base.py
artifact_experiment/_base/components/resources/cache.py
artifact_experiment/_base/components/resources/export.py
artifact_experiment/_base/components/resources/tracking.py
artifact_experiment/_base/primitives/__init__.py
artifact_experiment/_base/primitives/data_split.py
artifact_experiment/_base/primitives/file.py
artifact_experiment/_base/tracking/__init__.py
artifact_experiment/_base/tracking/backend/__init__.py
artifact_experiment-0.1.10.dist-info/METADATA
artifact_experiment-0.1.10.dist-info/WHEEL
artifact_experiment-0.1.10.dist-info/RECORD
