Metadata-Version: 2.4
Name: artifact-experiment
Version: 0.1.10
Summary: Artifact-ML experiment orchestration: declarative builder toolkit for reusable validation workflows with integrated tracking.
License: MIT
Author: Vasileios Ektor Papoulias
Author-email: hector.papoulias@gmail.com
Requires-Python: >=3.11,<3.14
Classifier: License :: OSI Approved :: MIT License
Classifier: Programming Language :: Python :: 3
Classifier: Programming Language :: Python :: 3.11
Classifier: Programming Language :: Python :: 3.12
Classifier: Programming Language :: Python :: 3.13
Requires-Dist: artifact-core (>=0.1.4,<0.2.0)
Requires-Dist: clearml (>=2.0.0,<3.0.0)
Requires-Dist: ipywidgets (>=8.1.7,<9.0.0)
Requires-Dist: mlflow (>=2.22.0,<3.0.0)
Requires-Dist: neptune (>=1.14.0,<2.0.0)
Requires-Dist: tqdm (>=4.67.1,<5.0.0)
Project-URL: Bug Tracker, https://github.com/vasileios-ektor-papoulias/artifact-ml/issues
Project-URL: Documentation, https://artifact-ml.readthedocs.io/en/latest/artifact-experiment
Project-URL: Homepage, https://github.com/vasileios-ektor-papoulias/artifact-ml
Project-URL: Repository, https://github.com/vasileios-ektor-papoulias/artifact-ml
